config.py
memory/__init__.py
memory/store.py
search/__init__.py
search/bm25.py
search/indexer.py
search/vector.py
server.py
vault/__init__.py
vault/reader.py
obsidian_vault_mcp-1.1.0.dist-info/METADATA
obsidian_vault_mcp-1.1.0.dist-info/WHEEL
obsidian_vault_mcp-1.1.0.dist-info/entry_points.txt
obsidian_vault_mcp-1.1.0.dist-info/licenses/LICENSE
obsidian_vault_mcp-1.1.0.dist-info/RECORD
