Metadata-Version: 2.4
Name: obsidian-vault-mcp
Version: 1.1.0
Summary: Obsidian Vault MCP - 语义搜索和记忆服务
Project-URL: Homepage, https://github.com/chyax98/obsidian-mcp
Project-URL: Repository, https://github.com/chyax98/obsidian-mcp
Author-email: chyax98 <chyax98@gmail.com>
License-Expression: MIT
License-File: LICENSE
Keywords: knowledge-base,mcp,obsidian,search,semantic
Classifier: Development Status :: 4 - Beta
Classifier: Intended Audience :: Developers
Classifier: License :: OSI Approved :: MIT License
Classifier: Programming Language :: Python :: 3.12
Classifier: Programming Language :: Python :: 3.13
Classifier: Topic :: Text Processing :: Indexing
Requires-Python: >=3.12
Requires-Dist: bm25s>=0.2.14
Requires-Dist: fastembed>=0.7.4
Requires-Dist: fastmcp>=2.14.1
Requires-Dist: jieba>=0.42.1
Requires-Dist: lancedb>=0.26.0
Requires-Dist: networkx>=3.6.1
Requires-Dist: psutil>=7.2.0
Requires-Dist: scipy>=1.16.3
